interpolation_engine/__init__.py
interpolation_engine/filter.py
interpolation_engine/interpolation_engine.py
interpolation_engine/show_tokens.py
interpolation_engine-1.5.0.dist-info/licenses/LICENSE
interpolation_engine-1.5.0.dist-info/METADATA
interpolation_engine-1.5.0.dist-info/WHEEL
interpolation_engine-1.5.0.dist-info/entry_points.txt
interpolation_engine-1.5.0.dist-info/top_level.txt
interpolation_engine-1.5.0.dist-info/RECORD
