Metadata-Version: 2.4
Name: interpolation-engine
Version: 1.5.0
Summary: A String Interpolation Automaton
Author: Till Falko Hofmann
License-Expression: MIT
Project-URL: Repository, https://github.com/tillfalko/interpolation-engine
Requires-Python: >=3.9
License-File: LICENSE
Requires-Dist: json5
Requires-Dist: openai
Requires-Dist: prompt_toolkit
Requires-Dist: pydantic
Dynamic: license-file
